darlog/__init__.py
darlog-0.0.1a0.dist-info/METADATA
darlog-0.0.1a0.dist-info/WHEEL
darlog-0.0.1a0.dist-info/top_level.txt
darlog-0.0.1a0.dist-info/RECORD
