Metadata-Version: 2.1
Name: darlog
Version: 0.0.1a0
Summary: Just an empty repo / PyPI package, created to take the namespace for my future python modules.
Home-page: https://github.com/Lex-DRL/darlog
Author: Lex Darlog (Lex-DRL)
Maintainer: Lex Darlog (Lex-DRL)
License: UNKNOWN
Keywords: placeholder,dummy,namespace
Platform: UNKNOWN
Classifier: Development Status :: 1 - Planning
Classifier: Intended Audience :: Developers
Classifier: Natural Language :: English
Classifier: Operating System :: OS Independent
Classifier: Programming Language :: Python
Classifier: Programming Language :: Python :: 2
Classifier: Programming Language :: Python :: 2.7
Classifier: Programming Language :: Python :: 3
Classifier: Topic :: Software Development :: Libraries :: Python Modules
Requires-Python: >=2.7
Provides-Extra: dev
Requires-Dist: darlog-pypi ; extra == 'dev'
